[
  {
    "sample": 40,
    "path": "sample0000040.pt",
    "bytes": 5902602,
    "k_gap_sampled": 0.31363755464553833,
    "v_gap_sampled": 0.4898877739906311,
    "h_gap_sampled": 0.5556117296218872,
    "attn_gap_sampled": 0.6708315014839172,
    "vproj_cache_mismatch": 0.0,
    "layer0_k_gap": 0.0004638170648831874,
    "layer0_v_gap": 0.00020387394761200994,
    "layer0_h_gap": 0.0,
    "layer0_attn_gap": 0.2663387954235077
  },
  {
    "sample": 41,
    "path": "sample0000041.pt",
    "bytes": 5902602,
    "k_gap_sampled": 0.3499717712402344,
    "v_gap_sampled": 0.5415419936180115,
    "h_gap_sampled": 0.5739560723304749,
    "attn_gap_sampled": 0.6158873438835144,
    "vproj_cache_mismatch": 0.0,
    "layer0_k_gap": 0.0004883687943220139,
    "layer0_v_gap": 5.5890559451654553e-05,
    "layer0_h_gap": 0.0,
    "layer0_attn_gap": 0.20715603232383728
  },
  {
    "sample": 42,
    "path": "sample0000042.pt",
    "bytes": 5902602,
    "k_gap_sampled": 0.34412169456481934,
    "v_gap_sampled": 0.5214623808860779,
    "h_gap_sampled": 0.5649197101593018,
    "attn_gap_sampled": 0.7053331732749939,
    "vproj_cache_mismatch": 0.0,
    "layer0_k_gap": 0.000470299826702103,
    "layer0_v_gap": 0.00020636127737816423,
    "layer0_h_gap": 0.0,
    "layer0_attn_gap": 0.3132353723049164
  },
  {
    "sample": 43,
    "path": "sample0000043.pt",
    "bytes": 5902602,
    "k_gap_sampled": 0.3130651116371155,
    "v_gap_sampled": 0.45033180713653564,
    "h_gap_sampled": 0.5021781325340271,
    "attn_gap_sampled": 0.734802782535553,
    "vproj_cache_mismatch": 0.0,
    "layer0_k_gap": 0.0004634169163182378,
    "layer0_v_gap": 6.30331996944733e-05,
    "layer0_h_gap": 0.0,
    "layer0_attn_gap": 0.27294644713401794
  },
  {
    "sample": 44,
    "path": "sample0000044.pt",
    "bytes": 5902602,
    "k_gap_sampled": 0.3283485174179077,
    "v_gap_sampled": 0.8542707562446594,
    "h_gap_sampled": 0.7127419114112854,
    "attn_gap_sampled": 0.5854165554046631,
    "vproj_cache_mismatch": 0.0,
    "layer0_k_gap": 0.00044993849587626755,
    "layer0_v_gap": 0.00010805074998643249,
    "layer0_h_gap": 0.0,
    "layer0_attn_gap": 0.22838382422924042
  },
  {
    "sample": 45,
    "path": "sample0000045.pt",
    "bytes": 5902602,
    "k_gap_sampled": 0.31378260254859924,
    "v_gap_sampled": 0.5569704174995422,
    "h_gap_sampled": 0.5688863396644592,
    "attn_gap_sampled": 0.745303213596344,
    "vproj_cache_mismatch": 0.0,
    "layer0_k_gap": 0.0004917361657135189,
    "layer0_v_gap": 5.9842215705430135e-05,
    "layer0_h_gap": 0.0,
    "layer0_attn_gap": 0.2472204864025116
  },
  {
    "sample": 46,
    "path": "sample0000046.pt",
    "bytes": 5902602,
    "k_gap_sampled": 0.317241370677948,
    "v_gap_sampled": 0.46178504824638367,
    "h_gap_sampled": 0.469483882188797,
    "attn_gap_sampled": 0.5576040148735046,
    "vproj_cache_mismatch": 0.0,
    "layer0_k_gap": 0.0004622349515557289,
    "layer0_v_gap": 0.00010083019151352346,
    "layer0_h_gap": 0.0,
    "layer0_attn_gap": 0.27038756012916565
  },
  {
    "sample": 47,
    "path": "sample0000047.pt",
    "bytes": 5902602,
    "k_gap_sampled": 0.31665128469467163,
    "v_gap_sampled": 0.3625466525554657,
    "h_gap_sampled": 0.4681352972984314,
    "attn_gap_sampled": 0.5698614120483398,
    "vproj_cache_mismatch": 0.0,
    "layer0_k_gap": 0.0004830143298022449,
    "layer0_v_gap": 5.522382343770005e-05,
    "layer0_h_gap": 0.0,
    "layer0_attn_gap": 0.2768027186393738
  }
]
