{
  "raw_rows": 1595,
  "summary": [
    {
      "dataset": "hotpotqa-v2",
      "method": "offline32b_top2",
      "rate": "0.15",
      "rows": 260,
      "expected_rows": 260,
      "complete": true,
      "glm_correct": 225,
      "glm_acc": 0.8653846153846154
    },
    {
      "dataset": "hotpotqa-v2",
      "method": "offline3b_freq_boundary2",
      "rate": "0.15",
      "rows": 260,
      "expected_rows": 260,
      "complete": true,
      "glm_correct": 224,
      "glm_acc": 0.8615384615384616
    },
    {
      "dataset": "hotpotqa-v2",
      "method": "offline3b_mean",
      "rate": "0.15",
      "rows": 260,
      "expected_rows": 260,
      "complete": true,
      "glm_correct": 227,
      "glm_acc": 0.8730769230769231
    },
    {
      "dataset": "triviaqa-v2",
      "method": "offline32b_top2",
      "rate": "0.15",
      "rows": 270,
      "expected_rows": 270,
      "complete": true,
      "glm_correct": 236,
      "glm_acc": 0.8740740740740741
    },
    {
      "dataset": "triviaqa-v2",
      "method": "offline3b_freq_boundary2",
      "rate": "0.15",
      "rows": 270,
      "expected_rows": 270,
      "complete": true,
      "glm_correct": 234,
      "glm_acc": 0.8666666666666667
    },
    {
      "dataset": "triviaqa-v2",
      "method": "offline3b_mean",
      "rate": "0.15",
      "rows": 270,
      "expected_rows": 270,
      "complete": true,
      "glm_correct": 237,
      "glm_acc": 0.8777777777777778
    }
  ]
}